sftpretty/__init__.py
sftpretty/exceptions.py
sftpretty/helpers.py
sftpretty-1.2.0.dist-info/METADATA
sftpretty-1.2.0.dist-info/WHEEL
sftpretty-1.2.0.dist-info/entry_points.txt
sftpretty-1.2.0.dist-info/licenses/LICENSE
sftpretty-1.2.0.dist-info/RECORD
