Metadata-Version: 2.4
Name: sftpretty
Version: 1.2.0
Summary: Pretty secure file transfer made easy.
Project-URL: Documentation, https://docs.sftpretty.com
Project-URL: Repository, https://github.com/byteskeptical/sftpretty
Project-URL: Tracker, https://github.com/byteskeptical/sftpretty/issues
Author: byteskeptical
License: BSD 3-Clause License
License-File: LICENSE
Keywords: file-transfer,file-transfer-protocol,ftp,paramiko,pysftp,scp,sftp,sftp-client,sftp-download,sftp-server,sftp-upload,ssh
Classifier: Development Status :: 5 - Production/Stable
Classifier: Environment :: Console
Classifier: Intended Audience :: Developers
Classifier: Intended Audience :: Information Technology
Classifier: Intended Audience :: System Administrators
Classifier: License :: OSI Approved :: BSD License
Classifier: Operating System :: OS Independent
Classifier: Programming Language :: Python :: 3
Classifier: Programming Language :: Python :: 3.6
Classifier: Programming Language :: Python :: 3.7
Classifier: Programming Language :: Python :: 3.8
Classifier: Programming Language :: Python :: 3.9
Classifier: Programming Language :: Python :: 3.10
Classifier: Programming Language :: Python :: 3.11
Classifier: Programming Language :: Python :: 3.12
Classifier: Programming Language :: Python :: 3.13
Classifier: Programming Language :: Python :: 3.14
Classifier: Programming Language :: Python :: Implementation :: CPython
Requires-Python: >=3.6
Requires-Dist: paramiko>=2.7.0
Provides-Extra: dev
Requires-Dist: pylint; extra == 'dev'
Provides-Extra: doc
Requires-Dist: babel; extra == 'doc'
Requires-Dist: docutils; extra == 'doc'
Requires-Dist: jinja2; extra == 'doc'
Requires-Dist: pygments; extra == 'doc'
Requires-Dist: sphinx; extra == 'doc'
Requires-Dist: sphinx-rtd-theme; extra == 'doc'
Provides-Extra: lint
Requires-Dist: pep8; extra == 'lint'
Provides-Extra: test
Requires-Dist: pytest; extra == 'test'
Requires-Dist: pytest-sftpserver; extra == 'test'
